agi_med_protos/__init__.py
agi_med_protos/io_grpc.py
agi_med_protos/logging_configuration.py
agi_med_protos/ptag_framework.py
agi_med_protos/ptag_pb2.py
agi_med_protos/ptag_pb2.pyi
agi_med_protos/ptag_pb2_grpc.py
agi_med_protos/utils_inspect.py
agi_med_protos-7.1.2.dist-info/METADATA
agi_med_protos-7.1.2.dist-info/WHEEL
agi_med_protos-7.1.2.dist-info/top_level.txt
agi_med_protos-7.1.2.dist-info/RECORD
