Metadata-Version: 2.4
Name: agi_med_protos
Version: 7.1.2
Summary: GRPC utils for agi-med team
Author: AGI-MED-TEAM
Requires-Python: >=3.11
Requires-Dist: protobuf~=5.29.1
Requires-Dist: grpcio~=1.68.1
Requires-Dist: grpcio-tools~=1.68.1
Requires-Dist: loguru~=0.7.2
Requires-Dist: pydantic<=3.0.0,>=2.9.2
